noload/__init__.py
noload/analyse/simulation.py
noload/gui/OpenGUI.py
noload/gui/gui1.py
noload/gui/gui2.py
noload/gui/plotIterations.py
noload/gui/plotPareto.py
noload/gui/testOverLabels.py
noload/optimization/ExportToXML.py
noload/optimization/Tools.py
noload/optimization/iterationHandler.py
noload/optimization/multiobjective.py
noload/optimization/optimProblem.py
noload/optimization/paretoTools.py
noload/optimization/specifications.py
noload/optimization/wrapper.py
noload/tutorial/01-UnconstrainedMonoObjective.py
noload/tutorial/02-ConstrainedMonoObjective.py
noload/tutorial/03-ConstrainedMultiObjective.py
noload/tutorial/04-ConstrainedMonoObjective2.py
noload/tutorial/05_SensitivityAnalysis.py
noload/tutorial/plotTools.py
noload-1.2.8.dist-info/AUTHORS.md
noload-1.2.8.dist-info/LICENSE
noload-1.2.8.dist-info/METADATA
noload-1.2.8.dist-info/WHEEL
noload-1.2.8.dist-info/top_level.txt
noload-1.2.8.dist-info/RECORD
