Metadata-Version: 2.1
Name: noload
Version: 1.2.8
Summary: solving constrained optimization problem for the design of engineering systems
Author: B. DELINCHANT, L. GERBAUD, F. WURTZ, L. AGOBERT
Author-email: benoit.delinchant@G2ELab.grenoble-inp.fr
Classifier: Programming Language :: Python
Classifier: License :: OSI Approved :: Apache Software License
Classifier: Programming Language :: Python :: 3.6
Classifier: Topic :: Scientific/Engineering
License-File: LICENSE
License-File: AUTHORS.md
Requires-Dist: Matplotlib (>3.0)
Requires-Dist: Scipy (>=1.2)
Requires-Dist: Autograd (>=1.2)
Requires-Dist: Pandas (>=1.3.5)
Requires-Dist: tk (>=0.1.0)
Requires-Dist: openpyxl (>=3.1.2)
